[
  {
    "date_found": "2026-06-30",
    "category": "新发布",
    "level": "A",
    "city": "上海",
    "organization": "上海市第十人民医院暨同济大学附属第十人民医院",
    "department": "医学科研岗位",
    "job_title": "医学科研人员",
    "requirements": "生命科学或医学相关专业博士学位；科研基础良好；熟练掌握相关领域实验技术；有 SCI 论文或主持科研项目经历者优先。外省市社会人员需上海居住证满一年，高级技术人员可放宽。",
    "posted_date": "2026-06-30",
    "deadline": "2026-07-18",
    "application_route": "电子邮件报名，将简历和相关证书扫描件发送至 rsk1520@163.com。",
    "source_url": "https://rsj.sh.gov.cn/tzpgg_17408/20260630/t0035_1441918.html",
    "source_type": "municipal_hr_official_hospital",
    "evidence": "上海人社 2026-06-30 新公告明确医学科研岗位职数 4 名、报名截止 2026-07-18，条件为生命科学或医学相关专业博士学位，邮箱和地址完整。",
    "suitability_reason": "三甲综合医院正式医学科研岗，专业口径宽于上一轮，博士学历和实验技术要求与曹博士病原生物学科研训练存在交叉。",
    "risks": "命中 12/14/51 既有上海十院医学科研人员 A 档基线，属于同单位同部门同岗位的新发布重发版，应更新时效但不重复计入新增 AB。",
    "status": "excluded",
    "key_hash": "2d2093a97a"
  },
  {
    "date_found": "2026-06-30",
    "category": "新发布",
    "level": "B",
    "city": "上海",
    "organization": "上海中医药大学附属岳阳中西医结合医院松江分院",
    "department": "免疫研究所",
    "job_title": "临床科研人才储备",
    "requirements": "临床科研人才储备 1 名；相关专业研究背景；国家级数据中心工作经历优先；有交叉学科研究经历；博士后研究背景；第一作者论文要求含《自然·通讯》《美国国家科学院院刊》《肿瘤学前沿》。",
    "posted_date": "2026-06-30",
    "deadline": "2026-07-08 17:00",
    "application_route": "按要求打包身份证、学历学位、职称资格和成果材料，发送至 yyyyrsc@163.com。",
    "source_url": "https://rsj.sh.gov.cn/tzpgg_17408/20260630/t0035_1441917.html",
    "source_type": "municipal_hr_official_hospital",
    "evidence": "上海人社 2026-06-30 新公告把松江分院临床科研人才储备细化为智慧医疗 1 名和免疫研究所 1 名；附件岗位职责写明免疫研究所方向为生殖系干细胞分化、肿瘤细胞空间三维表观遗传调控。",
    "suitability_reason": "相比 6 月 23 日版本，今天首次拆出免疫研究所方向，至少具备岗位级拆分证据，可作为医院科研岗更新线索留档。",
    "risks": "岗位要求博士后背景和顶刊一作，研究主题偏干细胞与肿瘤表观遗传调控，不是曹博士病原/病毒主线；整体门槛明显高于当前画像。",
    "status": "excluded",
    "key_hash": "3dcc5f417e"
  },
  {
    "date_found": "2026-06-30",
    "category": "新发布",
    "level": "B",
    "city": "上海",
    "organization": "上海中医药大学附属岳阳中西医结合医院松江分院",
    "department": "智慧医疗",
    "job_title": "临床科研人才储备",
    "requirements": "临床科研人才储备 1 名；相关专业研究背景；国家级数据中心工作经历优先；有交叉学科研究经历；博士后研究背景；第一作者论文要求含《自然·通讯》《美国国家科学院院刊》《肿瘤学前沿》。",
    "posted_date": "2026-06-30",
    "deadline": "2026-07-08 17:00",
    "application_route": "按要求打包身份证、学历学位、职称资格和成果材料，发送至 yyyyrsc@163.com。",
    "source_url": "https://rsj.sh.gov.cn/tzpgg_17408/20260630/t0035_1441917.html",
    "source_type": "municipal_hr_official_hospital",
    "evidence": "同一 2026-06-30 上海人社新公告与附件首次拆出智慧医疗方向，岗位职责为大模型临床数据分析与智慧医疗项目实施。",
    "suitability_reason": "公告层面首次从泛化储备岗细化出智慧医疗方向，可作为今天的新发布岗位级线索。",
    "risks": "岗位要求博士后背景和高水平论文，且核心职责偏大模型临床数据与项目实施，和曹博士病原生物学科研主线偏离明显。",
    "status": "excluded",
    "key_hash": "bce13b874b"
  }
]